{
  "formatVersion": 1,
  "database": {
    "version": 3,
    "identityHash": "4cd0e419c0f40c695fc1101c4e624395",
    "entities": [
      {
        "tableName": "todo_list",
        "createSql": "CREATE TABLE IF NOT EXISTS `${TABLE_NAME}` (`id` INTEGER PRIMARY KEY AUTOINCREMENT NOT NULL, `name` TEXT)",
        "fields": [
          {
            "fieldPath": "id",
            "columnName": "id",
            "affinity": "INTEGER",
            "notNull": true
          },
          {
            "fieldPath": "name",
            "columnName": "name",
            "affinity": "TEXT",
            "notNull": false
          }
        ],
        "primaryKey": {
          "autoGenerate": true,
          "columnNames": [
            "id"
          ]
        },
        "indices": [],
        "foreignKeys": []
      },
      {
        "tableName": "todo_task",
        "createSql": "CREATE TABLE IF NOT EXISTS `${TABLE_NAME}` (`id` INTEGER PRIMARY KEY AUTOINCREMENT NOT NULL, `name` TEXT, `listId` INTEGER NOT NULL, `listPosition` INTEGER NOT NULL, `description` TEXT, `priority` TEXT NOT NULL, `deadline` INTEGER NOT NULL, `reminderTime` INTEGER NOT NULL, `progress` INTEGER NOT NULL, `numberSubtasks` INTEGER NOT NULL, `isDone` INTEGER NOT NULL, `isInTrash` INTEGER NOT NULL)",
        "fields": [
          {
            "fieldPath": "id",
            "columnName": "id",
            "affinity": "INTEGER",
            "notNull": true
          },
          {
            "fieldPath": "name",
            "columnName": "name",
            "affinity": "TEXT",
            "notNull": false
          },
          {
            "fieldPath": "listId",
            "columnName": "listId",
            "affinity": "INTEGER",
            "notNull": true
          },
          {
            "fieldPath": "listPosition",
            "columnName": "listPosition",
            "affinity": "INTEGER",
            "notNull": true
          },
          {
            "fieldPath": "description",
            "columnName": "description",
            "affinity": "TEXT",
            "notNull": false
          },
          {
            "fieldPath": "priority",
            "columnName": "priority",
            "affinity": "TEXT",
            "notNull": true
          },
          {
            "fieldPath": "deadline",
            "columnName": "deadline",
            "affinity": "INTEGER",
            "notNull": true
          },
          {
            "fieldPath": "reminderTime",
            "columnName": "reminderTime",
            "affinity": "INTEGER",
            "notNull": true
          },
          {
            "fieldPath": "progress",
            "columnName": "progress",
            "affinity": "INTEGER",
            "notNull": true
          },
          {
            "fieldPath": "numberSubtasks",
            "columnName": "numberSubtasks",
            "affinity": "INTEGER",
            "notNull": true
          },
          {
            "fieldPath": "isDone",
            "columnName": "isDone",
            "affinity": "INTEGER",
            "notNull": true
          },
          {
            "fieldPath": "isInTrash",
            "columnName": "isInTrash",
            "affinity": "INTEGER",
            "notNull": true
          }
        ],
        "primaryKey": {
          "autoGenerate": true,
          "columnNames": [
            "id"
          ]
        },
        "indices": [],
        "foreignKeys": []
      },
      {
        "tableName": "todo_subtask",
        "createSql": "CREATE TABLE IF NOT EXISTS `${TABLE_NAME}` (`id` INTEGER PRIMARY KEY AUTOINCREMENT NOT NULL, `name` TEXT, `taskId` INTEGER NOT NULL, `isDone` INTEGER NOT NULL, `isInTrash` INTEGER NOT NULL)",
        "fields": [
          {
            "fieldPath": "id",
            "columnName": "id",
            "affinity": "INTEGER",
            "notNull": true
          },
          {
            "fieldPath": "name",
            "columnName": "name",
            "affinity": "TEXT",
            "notNull": false
          },
          {
            "fieldPath": "taskId",
            "columnName": "taskId",
            "affinity": "INTEGER",
            "notNull": true
          },
          {
            "fieldPath": "isDone",
            "columnName": "isDone",
            "affinity": "INTEGER",
            "notNull": true
          },
          {
            "fieldPath": "isInTrash",
            "columnName": "isInTrash",
            "affinity": "INTEGER",
            "notNull": true
          }
        ],
        "primaryKey": {
          "autoGenerate": true,
          "columnNames": [
            "id"
          ]
        },
        "indices": [],
        "foreignKeys": []
      }
    ],
    "views": [],
    "setupQueries": [
      "CREATE TABLE IF NOT EXISTS room_master_table (id INTEGER PRIMARY KEY,identity_hash TEXT)",
      "INSERT OR REPLACE INTO room_master_table (id,identity_hash) VALUES(42, '4cd0e419c0f40c695fc1101c4e624395')"
    ]
  }
}